{
  "$schema": "https://biomejs.dev/schemas/2.0.6/schema.json",
  "linter": {
    "enabled": true,
    "rules": {
      "recommended": true,
      "suspicious": {
        "noExplicitAny": "off",
        "noArrayIndexKey": "warn"
      },
      "complexity": {
        "noStaticOnlyClass": "off",
        "useLiteralKeys": "warn",
        "noForEach": "off"
      },
      "correctness": {
        "noUnusedFunctionParameters": "off",
        "useHookAtTopLevel": "warn"
      },
      "style": {
        "useTemplate": "warn",
        "useConst": "warn",
        "noNonNullAssertion": "off"
      },
      "security": {
        "noDangerouslySetInnerHtml": "error"
      },
      "a11y": {
        "noStaticElementInteractions": "warn",
        "noSvgWithoutTitle": "warn",
        "useButtonType": "error"
      }
    }
  },
  "formatter": {
    "enabled": true,
    "indentStyle": "space",
    "indentWidth": 2,
    "lineWidth": 80
  },
  "javascript": {
    "formatter": {
      "enabled": true,
      "quoteStyle": "double",
      "semicolons": "always",
      "trailingCommas": "es5"
    }
  },
  "files": {
    "includes": [
      "src/**/*.ts",
      "src/**/*.tsx",
      "app/**/*.ts",
      "app/**/*.tsx",
      "components/**/*.ts",
      "components/**/*.tsx",
      "lib/**/*.ts",
      "lib/**/*.tsx"
    ],
    "experimentalScannerIgnores": [
      "**/node_modules/**",
      "**/.next/**",
      "**/dist/**",
      "**/test-results/**",
      "**/playwright-report/**",
      "**/coverage/**",
      "**/.turbo/**"
    ]
  }
}
