[
  {
    "timestamp": "2025-07-04T04:33:57.369Z",
    "level": "info",
    "message": "Core Trading Service initialized",
    "context": {
      "component": "CoreTradingService",
      "operation": "info",
      "paperTrading": true,
      "maxPositions": 5,
      "strategy": "conservative"
    },
    "component": "CoreTradingService",
    "operation": "info",
    "service": "mexc-sniper-bot",
    "environment": "test"
  },
  {
    "timestamp": "2025-07-04T04:33:57.370Z",
    "level": "warn",
    "message": "Auto-initializing Core Trading Service for critical operation",
    "context": {
      "component": "CoreTradingService",
      "operation": "ensureInitialized",
      "autoInitializing": true,
      "context": {
        "stack": "Error: \n    at CoreTradingService.ensureInitialized (/Users/neo/Developer/mexc-sniper-bot/src/services/trading/consolidated/core-trading/base-service.ts:882:29)\n    at CoreTradingService.getPerformanceMetrics (/Users/neo/Developer/mexc-sniper-bot/src/services/trading/consolidated/core-trading/base-service.ts:587:10)\n    at ConfidenceCalculator.getHistoricalSuccessBoost (/Users/neo/Developer/mexc-sniper-bot/src/core/pattern-detection/confidence-calculator.ts:560:52)\n    at ConfidenceCalculator.calculateReadyStateConfidence (/Users/neo/Developer/mexc-sniper-bot/src/core/pattern-detection/confidence-calculator.ts:110:31)\n    at PatternAnalyzer.detectReadyStatePattern (/Users/neo/Developer/mexc-sniper-bot/src/core/pattern-detection/pattern-analyzer.ts:113:13)\n    at /Users/neo/Developer/mexc-sniper-bot/tests/unit/core/pattern-detection/pattern-analyzer.test.ts:109:23\n    at file:///Users/neo/Developer/mexc-sniper-bot/node_modules/@vitest/runner/dist/chunk-hooks.js:752:20"
      }
    },
    "component": "CoreTradingService",
    "operation": "ensureInitialized",
    "service": "mexc-sniper-bot",
    "environment": "test"
  },
  {
    "timestamp": "2025-07-04T04:33:57.370Z",
    "level": "info",
    "message": "Performing synchronous auto-initialization...",
    "context": {
      "component": "CoreTradingService",
      "operation": "info"
    },
    "component": "CoreTradingService",
    "operation": "info",
    "service": "mexc-sniper-bot",
    "environment": "test"
  },
  {
    "timestamp": "2025-07-04T04:33:57.370Z",
    "level": "info",
    "message": "Synchronous auto-initialization completed successfully",
    "context": {
      "component": "CoreTradingService",
      "operation": "info"
    },
    "component": "CoreTradingService",
    "operation": "info",
    "service": "mexc-sniper-bot",
    "environment": "test"
  }
]